<?xml version="1.0" encoding="utf-8" ?>
<dwsync>
<file name="header.php" server="C:/wamp/www/BTCvedan/" local="131629866752858920" remote="131629866750000000" Dst="0" />
<file name="favicon.html" server="C:/wamp/www/BTCvedan/" local="131608533211085119" remote="131608533210000000" Dst="0" />
<file name="head.php" server="C:/wamp/www/BTCvedan/" local="131608533932786398" remote="131608533930000000" Dst="0" />
<file name="sidebar.php" server="C:/wamp/www/BTCvedan/" local="131625966701597329" remote="131625966700000000" Dst="0" />
<file name="jsfiles.php" server="C:/wamp/www/BTCvedan/" local="131613476089994019" remote="131613476080000000" Dst="0" />
<file name="index.php" server="C:/wamp/www/BTCvedan/" local="131613437942492107" remote="131613437940000000" Dst="0" />
<file name="admin-acount.php" server="C:/wamp/www/BTCvedan/" local="131549658610000000" remote="131549658610000000" Dst="0" />
<file name="all-users.php" server="C:/wamp/www/BTCvedan/" local="131613472526680209" remote="131613472520000000" Dst="0" />
<file name="cashout-history.php" server="C:/wamp/www/BTCvedan/" local="131549662810037214" remote="131549662810000000" Dst="0" />
<file name="create-admin-acount.php" server="C:/wamp/www/BTCvedan/" local="131605896623363293" remote="131605896620000000" Dst="0" />
<file name="deposit-history.php" server="C:/wamp/www/BTCvedan/" local="131608531485226406" remote="131608531480000000" Dst="0" />
<file name="edit-admin.php" server="C:/wamp/www/BTCvedan/" local="131549658199773522" remote="131549658190000000" Dst="0" />
<file name="edit-news.php" server="C:/wamp/www/BTCvedan/" local="131549919247234327" remote="131549919240000000" Dst="0" />
<file name="login.php" server="C:/wamp/www/BTCvedan/" local="131625842009306179" remote="131625842000000000" Dst="0" />
<file name="new-view.php" server="C:/wamp/www/BTCvedan/" local="131549931576869541" remote="131549931570000000" Dst="0" />
<file name="pay-bitcoin.php" server="C:/wamp/www/BTCvedan/" local="131608536820371558" remote="131608536820000000" Dst="0" />
<file name="post-news.php" server="C:/wamp/www/BTCvedan/" local="131550369221972735" remote="131550369220000000" Dst="0" />
<file name="referral-history.php" server="C:/wamp/www/BTCvedan/" local="131549931935780070" remote="131549931930000000" Dst="0" />
<file name="respond-ticket.php" server="C:/wamp/www/BTCvedan/" local="131549936653049882" remote="131549936650000000" Dst="0" />
<file name="search-part.php" server="C:/wamp/www/BTCvedan/" local="131541552880000000" remote="131541552880000000" Dst="0" />
<file name="search-participant.php" server="C:/wamp/www/BTCvedan/" local="131549666651396928" remote="131549666650000000" Dst="0" />
<file name="search-participant2.php" server="C:/wamp/www/BTCvedan/" local="131549639432140075" remote="131549639430000000" Dst="0" />
<file name="user-profile.php" server="C:/wamp/www/BTCvedan/" local="131642901829459909" remote="131642901820000000" Dst="0" />
<file name="wallet.php" server="C:/wamp/www/BTCvedan/" local="131608547161613044" remote="131608547160000000" Dst="0" />
<file name="favicon.html" server="C:/wamp/www/ACADmovi/" local="131654056928906612" remote="131654056920000000" Dst="0" />
<file name="head.php" server="C:/wamp/www/ACADmovi/" local="131608533932786398" remote="131608533930000000" Dst="0" />
<file name="header.php" server="C:/wamp/www/ACADmovi/" local="131654052178694915" remote="131654052170000000" Dst="0" />
<file name="sidebar.php" server="C:/wamp/www/ACADmovi/" local="131625966701597329" remote="131625966700000000" Dst="0" />
<file name="jsfiles.php" server="C:/wamp/www/ACADmovi/" local="131613476089994019" remote="131613476080000000" Dst="0" />
<file name="index.php" server="C:/wamp/www/ACADmovi/" local="131654045409067715" remote="131654045400000000" Dst="0" />
<file name="404.html" server="C:/wamp/www/ACADmovi/" local="131654065621153780" remote="131654065620000000" Dst="0" />
<file name="wallet.php" server="C:/wamp/www/ACADmovi/" local="131654084141613090" remote="131654084140000000" Dst="0" />
<file name="search-participant2.php" server="C:/wamp/www/ACADmovi/" local="131654076488385350" remote="131654076480000000" Dst="0" />
<file name="search-participant.php" server="C:/wamp/www/ACADmovi/" local="131654080653603587" remote="131654080650000000" Dst="0" />
<file name="all-users.php" server="C:/wamp/www/ACADmovi/" local="131654082975996420" remote="131654082970000000" Dst="0" />
<file name="edit-wallet.php" server="C:/wamp/www/ACADmovi/" local="131654150969495426" remote="131654150960000000" Dst="0" />
<file name="favicon.html" server="C:/wamp/www/ALPHA-PACK/" local="131654056920000000" remote="131654056920000000" Dst="0" />
<file name="head.php" server="C:/wamp/www/ALPHA-PACK/" local="131608533920000000" remote="131608533920000000" Dst="0" />
<file name="header.php" server="C:/wamp/www/ALPHA-PACK/" local="131679413130221668" remote="131679413130000000" Dst="0" />
<file name="sidebar.php" server="C:/wamp/www/ALPHA-PACK/" local="131768502177569223" remote="131768502170000000" Dst="0" />
<file name="jsfiles.php" server="C:/wamp/www/ALPHA-PACK/" local="131679412775811397" remote="131679412770000000" Dst="0" />
<file name="index.php" server="C:/wamp/www/ALPHA-PACK/" local="131679416113062277" remote="131679416110000000" Dst="0" />
<file name="admin-acount.php" server="C:/wamp/www/ALPHA-PACK/" local="131679411294736684" remote="131679411290000000" Dst="0" />
<file name="all-users.php" server="C:/wamp/www/ALPHA-PACK/" local="131679543237948804" remote="131679543230000000" Dst="0" />
<file name="cashout-history.php" server="C:/wamp/www/ALPHA-PACK/" local="131679414456017499" remote="131679414450000000" Dst="0" />
<file name="create-admin-acount.php" server="C:/wamp/www/ALPHA-PACK/" local="131679414591575253" remote="131679414590000000" Dst="0" />
<file name="deposit-history.php" server="C:/wamp/www/ALPHA-PACK/" local="131679414761644980" remote="131679414760000000" Dst="0" />
<file name="edit-admin.php" server="C:/wamp/www/ALPHA-PACK/" local="131679415094264005" remote="131679415090000000" Dst="0" />
<file name="edit-news.php" server="C:/wamp/www/ALPHA-PACK/" local="131679415568931154" remote="131679415560000000" Dst="0" />
<file name="edit-wallet.php" server="C:/wamp/www/ALPHA-PACK/" local="131679415825475828" remote="131679415820000000" Dst="0" />
<file name="login.php" server="C:/wamp/www/ALPHA-PACK/" local="131679417030554754" remote="131679417030000000" Dst="0" />
<file name="new-view.php" server="C:/wamp/www/ALPHA-PACK/" local="131679417331901990" remote="131679417330000000" Dst="0" />
<file name="pay-bitcoin.php" server="C:/wamp/www/ALPHA-PACK/" local="131768953096448863" remote="131768953090000000" Dst="0" />
<file name="post-news.php" server="C:/wamp/www/ALPHA-PACK/" local="131679541036582893" remote="131679541030000000" Dst="0" />
<file name="referral-history.php" server="C:/wamp/www/ALPHA-PACK/" local="131608539280000000" remote="131608539280000000" Dst="0" />
<file name="respond-ticket.php" server="C:/wamp/www/ALPHA-PACK/" local="131679539836784269" remote="131679539830000000" Dst="0" />
<file name="search-part.php" server="C:/wamp/www/ALPHA-PACK/" local="131608541120000000" remote="131608541120000000" Dst="0" />
<file name="user-profile.php" server="C:/wamp/www/ALPHA-PACK/" local="131679539255701033" remote="131679539250000000" Dst="0" />
<file name="wallet.php" server="C:/wamp/www/ALPHA-PACK/" local="131766405381179813" remote="131766405380000000" Dst="0" />
<file name="search-participant2.php" server="C:/wamp/www/ALPHA-PACK/" local="131654357340000000" remote="131654357340000000" Dst="0" />
<file name="create-withdrawal.php" server="C:/wamp/www/ALPHA-PACK/" local="131771982610000000" remote="131771982610000000" Dst="0" />
<file name="jason-php-code-processor2.php" server="C:/wamp/www/ALPHA-PACK/" local="131768510658404299" remote="131768510650000000" Dst="0" />
<file name="sidebar.php" server="C:/wamp/www/AlMON-PACK/" local="131794754458532685" remote="131794754450000000" Dst="0" />
<file name="favicon.html" server="C:/wamp/www/AlMON-PACK/" local="131654056920000000" remote="131654056920000000" Dst="0" />
<file name="head.php" server="C:/wamp/www/AlMON-PACK/" local="131608533920000000" remote="131608533920000000" Dst="0" />
<file name="header.php" server="C:/wamp/www/AlMON-PACK/" local="131793917897860201" remote="131793917890000000" Dst="0" />
<file name="jsfiles.php" server="C:/wamp/www/AlMON-PACK/" local="131679412775811397" remote="131679412770000000" Dst="0" />
<file name="index.php" server="C:/wamp/www/AlMON-PACK/" local="131793905810918868" remote="131793905810000000" Dst="0" />
<file name="pay-bitcoin.php" server="C:/wamp/www/AlMON-PACK/" local="131793907852755654" remote="131793907850000000" Dst="0" />
<file name="wallet.php" server="C:/wamp/www/AlMON-PACK/" local="131815103071420379" remote="131815103070000000" Dst="0" />
<file name="create-withdrawal.php" server="C:/wamp/www/AlMON-PACK/" local="131793915541525427" remote="131793915540000000" Dst="0" />
<file name="payment-settings.php" server="C:/wamp/www/AlMON-PACK/" local="131794756669729158" remote="131794756660000000" Dst="0" />
<file name="user-profile.php" server="C:/wamp/www/AlMON-PACK/" local="131679539255701033" remote="131679539250000000" Dst="0" />
<file name="header.php" server="C:/wamp/www/AFPET_PACK/" local="131895914747247390" remote="131895914740000000" Dst="1" />
<file name="favicon.html" server="C:/wamp/www/AFPET_PACK/" local="131654056920000000" remote="131654056920000000" Dst="1" />
<file name="head.php" server="C:/wamp/www/AFPET_PACK/" local="131608533920000000" remote="131608533920000000" Dst="1" />
<file name="sidebar.php" server="C:/wamp/www/AFPET_PACK/" local="131794754458532685" remote="131794754450000000" Dst="1" />
<file name="jsfiles.php" server="C:/wamp/www/AFPET_PACK/" local="131679412775811397" remote="131679412770000000" Dst="1" />
<file name="user-profile.php" server="C:/wamp/www/AFPET_PACK/" local="131898958629015437" remote="131898958620000000" Dst="1" />
<file name="pay-bitcoin.php" server="C:/wamp/www/AFPET_PACK/" local="131896525253844451" remote="131896525250000000" Dst="1" />
<file name="wallet.php" server="C:/wamp/www/AFPET_PACK/" local="131896525484750157" remote="131896525480000000" Dst="1" />
<file name="sidebar.php" server="C:/wamp/www/MUZI-PACK/" local="132140962280000000" remote="132140962280000000" Dst="0" />
<file name="favicon.html" server="C:/wamp/www/MUZI-PACK/" local="131654128920000000" remote="131654128920000000" Dst="0" />
<file name="head.php" server="C:/wamp/www/MUZI-PACK/" local="131608641920000000" remote="131608641920000000" Dst="0" />
<file name="header.php" server="C:/wamp/www/MUZI-PACK/" local="131896022740000000" remote="131896022740000000" Dst="0" />
<file name="jsfiles.php" server="C:/wamp/www/MUZI-PACK/" local="131679484760000000" remote="131679484760000000" Dst="0" />
<file name="user-profile.php" server="C:/wamp/www/MUZI-PACK/" local="132083923483081714" remote="132083923480000000" Dst="2" />
<file name="wallet.php" server="C:/wamp/www/MUZI-PACK/" local="132140658645731437" remote="132140658640000000" Dst="0" />
<file name="pay-bitcoin.php" server="C:/wamp/www/MUZI-PACK/" local="132140658534006777" remote="132140658530000000" Dst="0" />
<file name="payout-manipulate.php" server="C:/wamp/www/MUZI-PACK/" local="132296560472827030" remote="132296560470000000" Dst="0" />
<file name="edit-ref.php" server="C:/wamp/www/MUZI-PACK/" local="132306502844628259" remote="132306502840000000" Dst="0" />
<file name="referral-history.php" server="C:/wamp/www/MUZI-PACK/" local="132306505286378715" remote="132306505280000000" Dst="0" />
<file name="sidebar.php" server="C:/wamp/www/2020FEAST/" local="132403933884609213" remote="132403933880000000" Dst="0" />
<file name="favicon.html" server="C:/wamp/www/2020FEAST/" local="131654128920000000" remote="131654128920000000" Dst="0" />
<file name="head.php" server="C:/wamp/www/2020FEAST/" local="131608641920000000" remote="131608641920000000" Dst="0" />
<file name="header.php" server="C:/wamp/www/2020FEAST/" local="131896022740000000" remote="131896022740000000" Dst="0" />
<file name="jsfiles.php" server="C:/wamp/www/2020FEAST/" local="131679484760000000" remote="131679484760000000" Dst="0" />
<file name="clients-review.php" server="C:/wamp/www/2020FEAST/" local="132404158271388099" remote="132404158270000000" Dst="0" />
</dwsync>